colipri/__init__.py
colipri/checkpoint.py
colipri/configs/config.yaml
colipri/configs/model/default.yaml
colipri/configs/model/image_encoder/backbone/default.yaml
colipri/configs/model/image_encoder/default.yaml
colipri/configs/model/image_encoder/pooler/default.yaml
colipri/configs/model/image_encoder/projector/default.yaml
colipri/configs/model/text_encoder/backbone/default.yaml
colipri/configs/model/text_encoder/default.yaml
colipri/configs/model/text_encoder/pooler/default.yaml
colipri/configs/processor/default.yaml
colipri/configs/processor/image_transform/default.yaml
colipri/configs/processor/tokenizer/default.yaml
colipri/defaults.py
colipri/model/__init__.py
colipri/model/base.py
colipri/model/image.py
colipri/model/multimodal.py
colipri/model/text.py
colipri/pipelines.py
colipri/pooling.py
colipri/processor.py
colipri/sample_data.py
colipri/types.py
colipri-0.1.0.dist-info/WHEEL
colipri-0.1.0.dist-info/METADATA
colipri-0.1.0.dist-info/RECORD
