Metadata-Version: 2.3
Name: colipri
Version: 0.1.0
Summary: Vision-language encoder for chest CT scans and reports.
Author: Microsoft Health Futures
Author-email: Microsoft Health Futures <innereyedev@microsoft.com>
Requires-Dist: accelerate
Requires-Dist: dynamic-network-architectures>=0.4.3
Requires-Dist: huggingface-hub
Requires-Dist: hydra-core
Requires-Dist: jaxtyping
Requires-Dist: safetensors
Requires-Dist: timm<1.0.23
Requires-Dist: torchio>=0.21.1
Requires-Dist: tqdm
Requires-Dist: transformers
Requires-Dist: typer
Requires-Dist: lovely-tensors ; extra == 'demo'
Requires-Dist: matplotlib ; extra == 'demo'
Requires-Dist: scikit-learn ; extra == 'demo'
Requires-Dist: torchinfo ; extra == 'demo'
Requires-Python: >=3.10
Project-URL: Homepage, https://huggingface.co/microsoft/colipri
Project-URL: Source, https://huggingface.co/microsoft/colipri
Project-URL: Issue tracker, https://huggingface.co/microsoft/colipri/discussions/new
Project-URL: Documentation, https://huggingface.co/microsoft/colipri/blob/main/README.md
Provides-Extra: demo
